{ "compressionlevel":-1,
 "height":12,
 "infinite":false,
 "layers":[
        {
         "data":[26, 26, 26, 26, 26, 26, 26, 26, 26, 26, 26, 26,
            26, 26, 26, 26, 26, 26, 26, 26, 26, 26, 26, 26,
            26, 26, 26, 34, 27, 26, 26, 34, 27, 26, 26, 26,
            26, 34, 36, 32, 35, 26, 26, 37, 30, 36, 27, 26,
            26, 29, 31, 0, 30, 36, 36, 32, 0, 40, 28, 26,
            26, 34, 32, 0, 0, 0, 0, 0, 0, 30, 27, 26,
            26, 37, 0, 0, 0, 0, 0, 0, 0, 0, 39, 26,
            26, 38, 0, 0, 0, 0, 0, 0, 0, 0, 39, 26,
            26, 37, 0, 0, 0, 0, 0, 0, 0, 0, 35, 26,
            26, 38, 0, 40, 33, 31, 0, 40, 31, 0, 35, 26,
            26, 29, 33, 28, 26, 29, 33, 28, 29, 33, 28, 26,
            26, 26, 26, 26, 26, 26, 26, 26, 26, 26, 26, 26],
         "height":12,
         "id":1,
         "name":"Tile Layer 1",
         "opacity":1,
         "type":"tilelayer",
         "visible":true,
         "width":12,
         "x":0,
         "y":0
        }, 
        {
         "draworder":"topdown",
         "id":2,
         "name":"player",
         "objects":[
                {
                 "gid":18,
                 "height":256,
                 "id":100,
                 "name":"",
                 "rotation":0,
                 "type":"",
                 "visible":true,
                 "width":256,
                 "x":988.888,
                 "y":2229.61
                }],
         "opacity":1,
         "type":"objectgroup",
         "visible":true,
         "x":0,
         "y":0
        }, 
        {
         "id":3,
         "layers":[],
         "name":"constants",
         "opacity":1,
         "type":"group",
         "visible":true,
         "x":0,
         "y":0
        }, 
        {
         "draworder":"topdown",
         "id":4,
         "name":"enemies",
         "objects":[
                {
                 "gid":17,
                 "height":512,
                 "id":47,
                 "name":"2",
                 "rotation":0,
                 "type":"",
                 "visible":true,
                 "width":512,
                 "x":950.938,
                 "y":3444.14
                }, 
                {
                 "gid":17,
                 "height":512,
                 "id":48,
                 "name":"4",
                 "rotation":0,
                 "type":"",
                 "visible":true,
                 "width":512,
                 "x":3061.18,
                 "y":4954.71
                }, 
                {
                 "gid":17,
                 "height":512,
                 "id":49,
                 "name":"1",
                 "rotation":0,
                 "type":"",
                 "visible":true,
                 "width":512,
                 "x":1421.57,
                 "y":4370.22
                }, 
                {
                 "gid":17,
                 "height":512,
                 "id":51,
                 "name":"3",
                 "rotation":0,
                 "type":"",
                 "visible":true,
                 "width":512,
                 "x":2863.82,
                 "y":2973.51
                }],
         "opacity":1,
         "type":"objectgroup",
         "visible":true,
         "x":0,
         "y":0
        }, 
        {
         "draworder":"topdown",
         "id":5,
         "name":"trees",
         "objects":[
                {
                 "gid":24,
                 "height":512,
                 "id":74,
                 "name":"",
                 "rotation":0,
                 "type":"",
                 "visible":true,
                 "width":256,
                 "x":2771.69,
                 "y":3466.91
                }, 
                {
                 "gid":24,
                 "height":512,
                 "id":75,
                 "name":"",
                 "rotation":0,
                 "type":"",
                 "visible":true,
                 "width":256,
                 "x":2786.87,
                 "y":3709.82
                }, 
                {
                 "gid":24,
                 "height":512,
                 "id":76,
                 "name":"",
                 "rotation":0,
                 "type":"",
                 "visible":true,
                 "width":256,
                 "x":2802.05,
                 "y":3869.22
                }, 
                {
                 "gid":24,
                 "height":512,
                 "id":77,
                 "name":"",
                 "rotation":0,
                 "type":"",
                 "visible":true,
                 "width":256,
                 "x":2809.64,
                 "y":4051.4
                }, 
                {
                 "gid":24,
                 "height":512,
                 "id":80,
                 "name":"",
                 "rotation":0,
                 "type":"",
                 "visible":true,
                 "width":256,
                 "x":2688.19,
                 "y":3702.23
                }, 
                {
                 "gid":24,
                 "height":512,
                 "id":81,
                 "name":"",
                 "rotation":0,
                 "type":"",
                 "visible":true,
                 "width":256,
                 "x":2483.24,
                 "y":3558
                }, 
                {
                 "gid":24,
                 "height":512,
                 "id":82,
                 "name":"",
                 "rotation":0,
                 "type":"",
                 "visible":true,
                 "width":256,
                 "x":1331.41056338028,
                 "y":2565.83408450704
                }, 
                {
                 "gid":24,
                 "height":512,
                 "id":83,
                 "name":"",
                 "rotation":0,
                 "type":"",
                 "visible":true,
                 "width":256,
                 "x":2604.69,
                 "y":3633.91
                }, 
                {
                 "gid":24,
                 "height":512,
                 "id":84,
                 "name":"",
                 "rotation":0,
                 "type":"",
                 "visible":true,
                 "width":256,
                 "x":2612.28,
                 "y":3778.13
                }, 
                {
                 "gid":24,
                 "height":512,
                 "id":85,
                 "name":"",
                 "rotation":0,
                 "type":"",
                 "visible":true,
                 "width":256,
                 "x":2430.1,
                 "y":3755.36
                }, 
                {
                 "gid":24,
                 "height":512,
                 "id":86,
                 "name":"",
                 "rotation":0,
                 "type":"",
                 "visible":true,
                 "width":256,
                 "x":2270.7,
                 "y":3725
                }, 
                {
                 "gid":24,
                 "height":512,
                 "id":87,
                 "name":"",
                 "rotation":0,
                 "type":"",
                 "visible":true,
                 "width":256,
                 "x":2695.78,
                 "y":3854.04
                },
            
                {
                 "gid":24,
                 "height":512,
                 "id":88,
                 "name":"",
                 "rotation":0,
                 "type":"",
                 "visible":true,
                 "width":256,
                 "x":2528.78,
                 "y":3998.27
                }, 
                {
                 "gid":24,
                 "height":512,
                 "id":89,
                 "name":"",
                 "rotation":0,
                 "type":"",
                 "visible":true,
                 "width":256,
                 "x":2376.97,
                 "y":4134.9
                }, 
                {
                 "gid":24,
                 "height":512,
                 "id":90,
                 "name":"",
                 "rotation":0,
                 "type":"",
                 "visible":true,
                 "width":256,
                 "x":2961.46,
                 "y":3633.91
                }, 
                {
                 "gid":24,
                 "height":512,
                 "id":91,
                 "name":"",
                 "rotation":0,
                 "type":"",
                 "visible":true,
                 "width":256,
                 "x":3105.68,
                 "y":3474.5
                }, 
                {
                 "gid":24,
                 "height":512,
                 "id":92,
                 "name":"",
                 "rotation":0,
                 "type":"",
                 "visible":true,
                 "width":256,
                 "x":3227.14,
                 "y":3391
                }, 
                {
                 "gid":24,
                 "height":512,
                 "id":93,
                 "name":"",
                 "rotation":0,
                 "type":"",
                 "visible":true,
                 "width":256,
                 "x":2961.46,
                 "y":3755.36
                }, 
                {
                 "gid":24,
                 "height":512,
                 "id":94,
                 "name":"",
                 "rotation":0,
                 "type":"",
                 "visible":true,
                 "width":256,
                 "x":3136.05,
                 "y":3755.36
                }, 
                {
                 "gid":24,
                 "height":512,
                 "id":95,
                 "name":"",
                 "rotation":0,
                 "type":"",
                 "visible":true,
                 "width":256,
                 "x":3272.68,
                 "y":3755.36
                }, 
                {
                 "gid":24,
                 "height":512,
                 "id":96,
                 "name":"",
                 "rotation":0,
                 "type":"",
                 "visible":true,
                 "width":256,
                 "x":2969.05,
                 "y":3914.77
                }, 
                {
                 "gid":24,
                 "height":512,
                 "id":97,
                 "name":"",
                 "rotation":0,
                 "type":"",
                 "visible":true,
                 "width":256,
                 "x":3098.09,
                 "y":4051.4
                }, 
                {
                 "gid":24,
                 "height":512,
                 "id":98,
                 "name":"",
                 "rotation":0,
                 "type":"",
                 "visible":true,
                 "width":256,
                 "x":3151.23,
                 "y":4096.95
                }],
         "opacity":1,
         "type":"objectgroup",
         "visible":true,
         "x":0,
         "y":0
        }, 
        {
         "draworder":"topdown",
         "id":6,
         "name":"object",
         "objects":[],
         "opacity":1,
         "type":"objectgroup",
         "visible":true,
         "x":0,
         "y":0
        }, 
        {
         "draworder":"topdown",
         "id":7,
         "name":"cave",
         "objects":[
                {
                 "gid":25,
                 "height":512,
                 "id":99,
                 "name":"",
                 "rotation":0,
                 "type":"",
                 "visible":true,
                 "width":512,
                 "x":4593.73461538462,
                 "y":5126.05923076923
                }],
         "opacity":1,
         "type":"objectgroup",
         "visible":true,
         "x":0,
         "y":0
        }, 
        {
         "draworder":"topdown",
         "id":8,
         "name":"rock",
         "objects":[],
         "opacity":1,
         "type":"objectgroup",
         "visible":true,
         "x":0,
         "y":0
        }, 
        {
         "draworder":"topdown",
         "id":9,
         "name":"markers",
         "objects":[
                {
                 "gid":41,
                 "height":128,
                 "id":102,
                 "name":"3",
                 "rotation":0,
                 "type":"1",
                 "visible":true,
                 "width":128,
                 "x":3534.04,
                 "y":2842.24
                }, 
                {
                 "gid":41,
                 "height":128,
                 "id":103,
                 "name":"3",
                 "rotation":0,
                 "type":"2",
                 "visible":true,
                 "width":128,
                 "x":4065.4,
                 "y":2857.42
                }, 
                {
                 "gid":41,
                 "height":128,
                 "id":104,
                 "name":"3",
                 "rotation":0,
                 "type":"3",
                 "visible":true,
                 "width":128,
                 "x":4573.98,
                 "y":2842.24
                }, 
                {
                 "gid":41,
                 "height":128,
                 "id":105,
                 "name":"4",
                 "rotation":0,
                 "type":"1",
                 "visible":true,
                 "width":128,
                 "x":3647.91,
                 "y":4732.35
                }, 
                {
                 "gid":41,
                 "height":128,
                 "id":106,
                 "name":"4",
                 "rotation":0,
                 "type":"2",
                 "visible":true,
                 "width":128,
                 "x":4126.13,
                 "y":4694.39
                }, 
                {
                 "gid":41,
                 "height":128,
                 "id":107,
                 "name":"4",
                 "rotation":0,
                 "type":"3",
                 "visible":true,
                 "width":128,
                 "x":4771.34,
                 "y":4709.57
                }, 
                {
                 "gid":41,
                 "height":128,
                 "id":108,
                 "name":"2",
                 "rotation":0,
                 "type":"1",
                 "visible":true,
                 "width":128,
                 "x":1484.52,
                 "y":3267.32
                }, 
                {
                 "gid":41,
                 "height":128,
                 "id":109,
                 "name":"2",
                 "rotation":0,
                 "type":"2",
                 "visible":true,
                 "width":128,
                 "x":1765.38,
                 "y":3267.32
                }, 
                {
                 "gid":41,
                 "height":128,
                 "id":110,
                 "name":"2",
                 "rotation":0,
                 "type":"3",
                 "visible":true,
                 "width":128,
                 "x":1772.98,
                 "y":2918.14
                }, 
                {
                 "gid":41,
                 "height":128,
                 "id":111,
                 "name":"2",
                 "rotation":0,
                 "type":"4",
                 "visible":true,
                 "width":128,
                 "x":1772.98,
                 "y":2622.1
                }, 
                {
                 "gid":41,
                 "height":128,
                 "id":112,
                 "name":"1",
                 "rotation":0,
                 "type":"1",
                 "visible":true,
                 "width":128,
                 "x":1977.93,
                 "y":4223.76
                }, 
                {
                 "gid":41,
                 "height":128,
                 "id":113,
                 "name":"1",
                 "rotation":0,
                 "type":"2",
                 "visible":true,
                 "width":128,
                 "x":1977.93,
                 "y":4679.21
                },
            
                {
                 "gid":41,
                 "height":128,
                 "id":114,
                 "name":"1",
                 "rotation":0,
                 "type":"3",
                 "visible":true,
                 "width":128,
                 "x":945.577,
                 "y":4686.8
                }, 
                {
                 "gid":41,
                 "height":128,
                 "id":116,
                 "name":"1",
                 "rotation":0,
                 "type":"4",
                 "visible":true,
                 "width":128,
                 "x":968.35,
                 "y":4223.76
                }],
         "opacity":1,
         "type":"objectgroup",
         "visible":true,
         "x":0,
         "y":0
        }],
 "nextlayerid":10,
 "nextobjectid":117,
 "orientation":"orthogonal",
 "renderorder":"right-down",
 "tiledversion":"1.10.2",
 "tileheight":512,
 "tilesets":[
        {
         "firstgid":1,
         "source":"maps\/Polar_Cliff_center.tsx"
        }, 
        {
         "firstgid":2,
         "source":"maps\/Polar_Cliff_Corner_1.tsx"
        }, 
        {
         "firstgid":3,
         "source":"maps\/Polar_Cliff_Edge_4.tsx"
        }, 
        {
         "firstgid":4,
         "source":"maps\/Polar_Cliff_Corner_2.tsx"
        }, 
        {
         "firstgid":5,
         "source":"maps\/Polar_Cliff_Corner_6.tsx"
        }, 
        {
         "firstgid":6,
         "source":"maps\/Polar_Cliff_Corner_5.tsx"
        }, 
        {
         "firstgid":7,
         "source":"maps\/Polar_Cliff_Corner_4.tsx"
        }, 
        {
         "firstgid":8,
         "source":"maps\/Polar_Cliff_Corner_3.tsx"
        }, 
        {
         "firstgid":9,
         "source":"maps\/Polar_Cliff_Corner_7_large.tsx"
        }, 
        {
         "firstgid":10,
         "source":"maps\/Polar_Cliff_Edge_2.tsx"
        }, 
        {
         "firstgid":11,
         "source":"maps\/Polar_Cliff_Edge_3.tsx"
        }, 
        {
         "firstgid":12,
         "source":"maps\/Polar_Cliff_Edge_1.tsx"
        },
    
        {
         "firstgid":13,
         "source":"maps\/Polar_Cliff_Corner_8.tsx"
        }, 
        {
         "firstgid":14,
         "source":"maps\/Polar_Cliff_Edge_5.tsx"
        }, 
        {
         "firstgid":15,
         "source":"maps\/Polar_Cliff_Edge_6.tsx"
        }, 
        {
         "firstgid":16,
         "source":"maps\/polar_cliff_edge_left_side.tsx"
        }, 
        {
         "firstgid":17,
         "source":"maps\/salmon_walk_2_small.tsx"
        }, 
        {
         "firstgid":18,
         "source":"maps\/Ursa.tsx"
        }, 
        {
         "firstgid":24,
         "source":"maps\/tundra_tree_snow_small.tsx"
        }, 
        {
         "firstgid":25,
         "source":"maps\/cave.tsx"
        }, 
        {
         "firstgid":26,
         "source":"maps\/tiles.tsx"
        }, 
        {
         "firstgid":41,
         "source":"maps\/marker.tsx"
        }],
 "tilewidth":512,
 "type":"map",
 "version":"1.10",
 "width":12
}